setup.py
collective/__init__.py
collective.baseid.egg-info/PKG-INFO
collective.baseid.egg-info/SOURCES.txt
collective.baseid.egg-info/dependency_links.txt
collective.baseid.egg-info/entry_points.txt
collective.baseid.egg-info/namespace_packages.txt
collective.baseid.egg-info/not-zip-safe
collective.baseid.egg-info/requires.txt
collective.baseid.egg-info/top_level.txt
collective/baseid/__init__.py
collective/baseid/interfaces.py
docs/HISTORY.txt
docs/INSTALL.txt
docs/LICENSE.GPL
docs/LICENSE.ZPL
docs/LICENSE.txt
docs/README.txt
docs/TODO.txt